{"name":"adizya","dependencies":{"@types/json-schema":{"version":"7.0.9"},"ajv-keywords":{"version":"3.5.2"},"big.js":{"version":"5.2.2"},"doctrine":{"version":"2.1.0"},"emojis-list":{"version":"3.0.0"},"file-loader":{"version":"6.2.0"},"globals":{"version":"11.12.0"},"json5":{"version":"2.2.0"},"loader-utils":{"version":"2.0.2"},"mime-db":{"version":"1.51.0"},"mime-types":{"version":"2.1.34"},"next-images":{"version":"1.8.4"},"next":{"version":"12.0.10"},"react-dom":{"version":"17.0.2"},"react":{"version":"17.0.2"},"schema-utils":{"version":"3.1.1"},"semver":{"version":"6.3.0"},"url-loader":{"version":"4.1.1"}}}